spider_api/__init__.py
spider_api-2.4.dist-info/LICENSE
spider_api-2.4.dist-info/METADATA
spider_api-2.4.dist-info/WHEEL
spider_api-2.4.dist-info/top_level.txt
spider_api-2.4.dist-info/RECORD
